etp/__init__.py
etp/enhanced_threadpool_setup.py
etp-0.2.0.dist-info/METADATA
etp-0.2.0.dist-info/RECORD
etp-0.2.0.dist-info/WHEEL
etp-0.2.0.dist-info/top_level.txt
