Metadata-Version: 2.1
Name: etp
Version: 0.2.0
Summary: A ThreadPool extension
Home-page: https://github.com/dobbleg1000/enhanced_threadpool
Author: DobbleG1000
License: UNKNOWN
Platform: UNKNOWN
Classifier: Programming Language :: Python :: 3
Classifier: License :: OSI Approved :: GNU General Public License v3 (GPLv3)
Classifier: Operating System :: OS Independent
Classifier: Natural Language :: English
